coplan/__init__.py
coplan-0.0.0.dist-info/LICENSE
coplan-0.0.0.dist-info/METADATA
coplan-0.0.0.dist-info/WHEEL
coplan-0.0.0.dist-info/top_level.txt
coplan-0.0.0.dist-info/RECORD
